[
    {
        "mmsi": 210329000,
        "name": "RUSADIR",
        "lat": 36.60554333333334,
        "lon": -4.3042750000000005,
        "tooltip_title": "\ud83d\udea2 RUSADIR",
        "tooltip_content": "MMSI: 210329000"
    },
    {
        "mmsi": 255806022,
        "name": "MONTE UDALA         ",
        "lat": 36.11203166666667,
        "lon": -4.218096666666667,
        "tooltip_title": "\ud83d\udea2 MONTE UDALA         ",
        "tooltip_content": "MMSI: 255806022"
    },
    {
        "mmsi": 225991712,
        "name": "MUNDO MARINO ECO",
        "lat": 36.70503833333333,
        "lon": -4.390985,
        "tooltip_title": "\ud83d\udea2 MUNDO MARINO ECO",
        "tooltip_content": "MMSI: 225991712"
    },
    {
        "mmsi": 224853000,
        "name": "TRHEINTAYCINCO      ",
        "lat": 36.71058666666667,
        "lon": -4.422201666666667,
        "tooltip_title": "\ud83d\udea2 TRHEINTAYCINCO      ",
        "tooltip_content": "MMSI: 224853000"
    },
    {
        "mmsi": 225982867,
        "name": "FLY BLUE TRES",
        "lat": 36.71511666666667,
        "lon": -4.4158599999999995,
        "tooltip_title": "\ud83d\udea2 FLY BLUE TRES",
        "tooltip_content": "MMSI: 225982867"
    },
    {
        "mmsi": 224975000,
        "name": "TRHEINTAYCUATRO     ",
        "lat": 36.71068833333333,
        "lon": -4.421756666666667,
        "tooltip_title": "\ud83d\udea2 TRHEINTAYCUATRO     ",
        "tooltip_content": "MMSI: 224975000"
    },
    {
        "mmsi": 538071020,
        "name": "SHU U RITE          ",
        "lat": 36.717546666666664,
        "lon": -4.413503333333334,
        "tooltip_title": "\ud83d\udea2 SHU U RITE          ",
        "tooltip_content": "MMSI: 538071020"
    },
    {
        "mmsi": 224063870,
        "name": "MAGIC A ",
        "lat": 36.717815,
        "lon": -4.413336666666667,
        "tooltip_title": "\ud83d\udea2 MAGIC A ",
        "tooltip_content": "MMSI: 224063870"
    },
    {
        "mmsi": 304623000,
        "name": "KATHERINE BORCHARD",
        "lat": 36.199844999999996,
        "lon": -4.089931666666667,
        "tooltip_title": "\ud83d\udea2 KATHERINE BORCHARD",
        "tooltip_content": "MMSI: 304623000"
    },
    {
        "mmsi": 224094750,
        "name": "PAPELERO            ",
        "lat": 36.804206666666666,
        "lon": -6.33685,
        "tooltip_title": "\ud83d\udea2 PAPELERO            ",
        "tooltip_content": "MMSI: 224094750"
    },
    {
        "mmsi": 228299110,
        "name": "",
        "lat": 36.595,
        "lon": -4.51184,
        "tooltip_title": "\ud83d\udea2 ",
        "tooltip_content": "MMSI: 228299110"
    },
    {
        "mmsi": 309221000,
        "name": "LADY MOURA",
        "lat": 36.716469999999994,
        "lon": -4.414158333333333,
        "tooltip_title": "\ud83d\udea2 LADY MOURA",
        "tooltip_content": "MMSI: 309221000"
    }
]