[
    {
        "mmsi": 538012063,
        "name": "NAVIGATOR           ",
        "lat": 36.142601666666664,
        "lon": -4.557855,
        "tooltip_title": "\ud83d\udea2 NAVIGATOR           ",
        "tooltip_content": "MMSI: 538012063"
    },
    {
        "mmsi": 268261600,
        "name": "OLD WINE            ",
        "lat": 36.03753666666667,
        "lon": -4.951686666666666,
        "tooltip_title": "\ud83d\udea2 OLD WINE            ",
        "tooltip_content": "MMSI: 268261600"
    },
    {
        "mmsi": 636026162,
        "name": "MIREA               ",
        "lat": 35.82163333333333,
        "lon": -4.921883333333333,
        "tooltip_title": "\ud83d\udea2 MIREA               ",
        "tooltip_content": "MMSI: 636026162"
    },
    {
        "mmsi": 636025571,
        "name": "JAXSON              ",
        "lat": 35.925489999999996,
        "lon": -4.798115,
        "tooltip_title": "\ud83d\udea2 JAXSON              ",
        "tooltip_content": "MMSI: 636025571"
    },
    {
        "mmsi": 209575000,
        "name": "CONTSHIP PAX",
        "lat": 36.08373666666667,
        "lon": -4.232081666666667,
        "tooltip_title": "\ud83d\udea2 CONTSHIP PAX",
        "tooltip_content": "MMSI: 209575000"
    },
    {
        "mmsi": 538004030,
        "name": "SEAWAYS FRIO        ",
        "lat": 36.06089166666666,
        "lon": -4.636733333333334,
        "tooltip_title": "\ud83d\udea2 SEAWAYS FRIO        ",
        "tooltip_content": "MMSI: 538004030"
    },
    {
        "mmsi": 229319000,
        "name": "SEASALVIA           ",
        "lat": 36.211043333333336,
        "lon": -4.95493,
        "tooltip_title": "\ud83d\udea2 SEASALVIA           ",
        "tooltip_content": "MMSI: 229319000"
    },
    {
        "mmsi": 255806313,
        "name": "KILIA               ",
        "lat": 36.18216666666667,
        "lon": -4.904843333333333,
        "tooltip_title": "\ud83d\udea2 KILIA               ",
        "tooltip_content": "MMSI: 255806313"
    },
    {
        "mmsi": 229648000,
        "name": "LEONIDIO            ",
        "lat": 35.76034166666667,
        "lon": -5.085455,
        "tooltip_title": "\ud83d\udea2 LEONIDIO            ",
        "tooltip_content": "MMSI: 229648000"
    },
    {
        "mmsi": 224096580,
        "name": "ESTELA Y MIRIAM",
        "lat": 36.78750166666667,
        "lon": -6.369543333333334,
        "tooltip_title": "\ud83d\udea2 ESTELA Y MIRIAM",
        "tooltip_content": "MMSI: 224096580"
    },
    {
        "mmsi": 563209600,
        "name": "HAFNIA VALENTINO    ",
        "lat": 36.225381666666664,
        "lon": -4.979501666666667,
        "tooltip_title": "\ud83d\udea2 HAFNIA VALENTINO    ",
        "tooltip_content": "MMSI: 563209600"
    },
    {
        "mmsi": 538071020,
        "name": "SHU U RITE          ",
        "lat": 36.717530000000004,
        "lon": -4.413503333333334,
        "tooltip_title": "\ud83d\udea2 SHU U RITE          ",
        "tooltip_content": "MMSI: 538071020"
    },
    {
        "mmsi": 215413000,
        "name": "AURETTE A           ",
        "lat": 35.85884333333333,
        "lon": -4.931423333333333,
        "tooltip_title": "\ud83d\udea2 AURETTE A           ",
        "tooltip_content": "MMSI: 215413000"
    },
    {
        "mmsi": 210312000,
        "name": "WEC MAJORELLE",
        "lat": 36.06095666666667,
        "lon": -5.267836666666667,
        "tooltip_title": "\ud83d\udea2 WEC MAJORELLE",
        "tooltip_content": "MMSI: 210312000"
    },
    {
        "mmsi": 215342000,
        "name": "CMACGMFORT ST PIERR",
        "lat": 35.884083333333336,
        "lon": -4.979583333333333,
        "tooltip_title": "\ud83d\udea2 CMACGMFORT ST PIERR",
        "tooltip_content": "MMSI: 215342000"
    },
    {
        "mmsi": 636023807,
        "name": "CSPC RUBY           ",
        "lat": 36.30519833333334,
        "lon": -4.664023333333334,
        "tooltip_title": "\ud83d\udea2 CSPC RUBY           ",
        "tooltip_content": "MMSI: 636023807"
    },
    {
        "mmsi": 563087400,
        "name": "SPETSES LADY        ",
        "lat": 36.023805,
        "lon": -4.8716349999999995,
        "tooltip_title": "\ud83d\udea2 SPETSES LADY        ",
        "tooltip_content": "MMSI: 563087400"
    },
    {
        "mmsi": 636026182,
        "name": "MAMMA MARIA         ",
        "lat": 35.780788333333334,
        "lon": -4.918293333333334,
        "tooltip_title": "\ud83d\udea2 MAMMA MARIA         ",
        "tooltip_content": "MMSI: 636026182"
    },
    {
        "mmsi": 215178000,
        "name": "MURRAY STAR         ",
        "lat": 36.13408833333334,
        "lon": -5.009081666666666,
        "tooltip_title": "\ud83d\udea2 MURRAY STAR         ",
        "tooltip_content": "MMSI: 215178000"
    },
    {
        "mmsi": 563315500,
        "name": "BW NIVALIS          ",
        "lat": 35.96507999999999,
        "lon": -6.3264949999999995,
        "tooltip_title": "\ud83d\udea2 BW NIVALIS          ",
        "tooltip_content": "MMSI: 563315500"
    },
    {
        "mmsi": 538010193,
        "name": "EVGENIA S",
        "lat": 35.82889,
        "lon": -5.004594999999999,
        "tooltip_title": "\ud83d\udea2 EVGENIA S",
        "tooltip_content": "MMSI: 538010193"
    },
    {
        "mmsi": 227334100,
        "name": "MACAPA              ",
        "lat": 36.51045,
        "lon": -4.561843333333333,
        "tooltip_title": "\ud83d\udea2 MACAPA              ",
        "tooltip_content": "MMSI: 227334100"
    },
    {
        "mmsi": 224249690,
        "name": "SAMA",
        "lat": 36.50552166666667,
        "lon": -4.567858333333334,
        "tooltip_title": "\ud83d\udea2 SAMA",
        "tooltip_content": "MMSI: 224249690"
    },
    {
        "mmsi": 352004281,
        "name": "MAERSK EL ALTO      ",
        "lat": 35.94858,
        "lon": -4.9740866666666665,
        "tooltip_title": "\ud83d\udea2 MAERSK EL ALTO      ",
        "tooltip_content": "MMSI: 352004281"
    },
    {
        "mmsi": 224014470,
        "name": "NEW MAGIC           ",
        "lat": 36.588205,
        "lon": -4.5100050000000005,
        "tooltip_title": "\ud83d\udea2 NEW MAGIC           ",
        "tooltip_content": "MMSI: 224014470"
    },
    {
        "mmsi": 636023978,
        "name": "CLARA B",
        "lat": 36.23149166666667,
        "lon": -5.019833333333334,
        "tooltip_title": "\ud83d\udea2 CLARA B",
        "tooltip_content": "MMSI: 636023978"
    },
    {
        "mmsi": 245535000,
        "name": "LOIREBORG           ",
        "lat": 36.212286666666664,
        "lon": -4.030976666666667,
        "tooltip_title": "\ud83d\udea2 LOIREBORG           ",
        "tooltip_content": "MMSI: 245535000"
    },
    {
        "mmsi": 224115170,
        "name": "HERMANOS CORPAS    ",
        "lat": 36.29768166666667,
        "lon": -4.962455,
        "tooltip_title": "\ud83d\udea2 HERMANOS CORPAS    ",
        "tooltip_content": "MMSI: 224115170"
    },
    {
        "mmsi": 220291000,
        "name": "LARS MAERSK",
        "lat": 35.93240166666667,
        "lon": -5.081003333333333,
        "tooltip_title": "\ud83d\udea2 LARS MAERSK",
        "tooltip_content": "MMSI: 220291000"
    },
    {
        "mmsi": 538007703,
        "name": "RG CERES            ",
        "lat": 36.04633666666667,
        "lon": -4.891193333333334,
        "tooltip_title": "\ud83d\udea2 RG CERES            ",
        "tooltip_content": "MMSI: 538007703"
    },
    {
        "mmsi": 224166440,
        "name": "HAROMAR SEGUNDO",
        "lat": 36.539105,
        "lon": -4.6170383333333325,
        "tooltip_title": "\ud83d\udea2 HAROMAR SEGUNDO",
        "tooltip_content": "MMSI: 224166440"
    }
]