[
    {
        "mmsi": 636024698,
        "name": "MC CALYPSO          ",
        "lat": 36.05893666666667,
        "lon": -4.9071,
        "tooltip_title": "\ud83d\udea2 MC CALYPSO          ",
        "tooltip_content": "MMSI: 636024698"
    },
    {
        "mmsi": 247238700,
        "name": "LEALE",
        "lat": 36.13914,
        "lon": -4.9799,
        "tooltip_title": "\ud83d\udea2 LEALE",
        "tooltip_content": "MMSI: 247238700"
    },
    {
        "mmsi": 242943000,
        "name": "SR MALABATA         ",
        "lat": 35.816795,
        "lon": -5.749628333333334,
        "tooltip_title": "\ud83d\udea2 SR MALABATA         ",
        "tooltip_content": "MMSI: 242943000"
    },
    {
        "mmsi": 304030000,
        "name": "NIKLAS              ",
        "lat": 36.06263166666667,
        "lon": -4.935466666666667,
        "tooltip_title": "\ud83d\udea2 NIKLAS              ",
        "tooltip_content": "MMSI: 304030000"
    },
    {
        "mmsi": 224070871,
        "name": "ANTONIO Y SARI ",
        "lat": 36.627253333333336,
        "lon": -4.3818399999999995,
        "tooltip_title": "\ud83d\udea2 ANTONIO Y SARI ",
        "tooltip_content": "MMSI: 224070871"
    },
    {
        "mmsi": 256536000,
        "name": "LEVANTE LNG         ",
        "lat": 36.018305000000005,
        "lon": -5.01665,
        "tooltip_title": "\ud83d\udea2 LEVANTE LNG         ",
        "tooltip_content": "MMSI: 256536000"
    },
    {
        "mmsi": 224593000,
        "name": "PASIO PER FORMENTERA",
        "lat": 35.895518333333335,
        "lon": -5.322651666666667,
        "tooltip_title": "\ud83d\udea2 PASIO PER FORMENTERA",
        "tooltip_content": "MMSI: 224593000"
    },
    {
        "mmsi": 273279600,
        "name": "AKSAY               ",
        "lat": 35.99115666666667,
        "lon": -4.99993,
        "tooltip_title": "\ud83d\udea2 AKSAY               ",
        "tooltip_content": "MMSI: 273279600"
    },
    {
        "mmsi": 242400000,
        "name": "CABO NEGRO          ",
        "lat": 35.68068,
        "lon": -5.290421666666666,
        "tooltip_title": "\ud83d\udea2 CABO NEGRO          ",
        "tooltip_content": "MMSI: 242400000"
    },
    {
        "mmsi": 229665000,
        "name": "DIMITRIS C          ",
        "lat": 35.921303333333334,
        "lon": -5.491485,
        "tooltip_title": "\ud83d\udea2 DIMITRIS C          ",
        "tooltip_content": "MMSI: 229665000"
    },
    {
        "mmsi": 413065000,
        "name": "XIN XIA MEN         ",
        "lat": 36.038691666666665,
        "lon": -6.482473333333333,
        "tooltip_title": "\ud83d\udea2 XIN XIA MEN         ",
        "tooltip_content": "MMSI: 413065000"
    },
    {
        "mmsi": 232041328,
        "name": "MR. MOURA",
        "lat": 36.49957166666666,
        "lon": -4.571668333333333,
        "tooltip_title": "\ud83d\udea2 MR. MOURA",
        "tooltip_content": "MMSI: 232041328"
    },
    {
        "mmsi": 209887000,
        "name": "LEDRA DYNAMIC",
        "lat": 35.856141666666666,
        "lon": -5.1736716666666664,
        "tooltip_title": "\ud83d\udea2 LEDRA DYNAMIC",
        "tooltip_content": "MMSI: 209887000"
    },
    {
        "mmsi": 538012685,
        "name": "AL KHIBEESI",
        "lat": 36.34647833333334,
        "lon": -4.170283333333334,
        "tooltip_title": "\ud83d\udea2 AL KHIBEESI",
        "tooltip_content": "MMSI: 538012685"
    },
    {
        "mmsi": 511101890,
        "name": "BBA LARISA          ",
        "lat": 36.326299999999996,
        "lon": -4.499105,
        "tooltip_title": "\ud83d\udea2 BBA LARISA          ",
        "tooltip_content": "MMSI: 511101890"
    },
    {
        "mmsi": 636093333,
        "name": "LIVORNO EXPRESS     ",
        "lat": 36.11639,
        "lon": -5.405353333333333,
        "tooltip_title": "\ud83d\udea2 LIVORNO EXPRESS     ",
        "tooltip_content": "MMSI: 636093333"
    },
    {
        "mmsi": 229548000,
        "name": "VALENCE             ",
        "lat": 36.188248333333334,
        "lon": -6.974131666666667,
        "tooltip_title": "\ud83d\udea2 VALENCE             ",
        "tooltip_content": "MMSI: 229548000"
    },
    {
        "mmsi": 304964000,
        "name": "KIRSI",
        "lat": 36.79189833333333,
        "lon": -6.803745,
        "tooltip_title": "\ud83d\udea2 KIRSI",
        "tooltip_content": "MMSI: 304964000"
    },
    {
        "mmsi": 224925000,
        "name": "OMVAC DOCE          ",
        "lat": 36.14073666666666,
        "lon": -5.337435,
        "tooltip_title": "\ud83d\udea2 OMVAC DOCE          ",
        "tooltip_content": "MMSI: 224925000"
    },
    {
        "mmsi": 376865000,
        "name": "PROTUG 87",
        "lat": 36.08635,
        "lon": -4.979568333333333,
        "tooltip_title": "\ud83d\udea2 PROTUG 87",
        "tooltip_content": "MMSI: 376865000"
    },
    {
        "mmsi": 224076970,
        "name": "DOLORES LAZO        ",
        "lat": 36.63356666666667,
        "lon": -4.3706483333333335,
        "tooltip_title": "\ud83d\udea2 DOLORES LAZO        ",
        "tooltip_content": "MMSI: 224076970"
    },
    {
        "mmsi": 636022640,
        "name": "SONGA PANTHER       ",
        "lat": 36.277116666666664,
        "lon": -4.923385,
        "tooltip_title": "\ud83d\udea2 SONGA PANTHER       ",
        "tooltip_content": "MMSI: 636022640"
    },
    {
        "mmsi": 215178000,
        "name": "MURRAY STAR         ",
        "lat": 36.26264666666667,
        "lon": -4.758961666666666,
        "tooltip_title": "\ud83d\udea2 MURRAY STAR         ",
        "tooltip_content": "MMSI: 215178000"
    },
    {
        "mmsi": 246591000,
        "name": "FAGELGRACHT         ",
        "lat": 36.13231833333334,
        "lon": -5.09017,
        "tooltip_title": "\ud83d\udea2 FAGELGRACHT         ",
        "tooltip_content": "MMSI: 246591000"
    },
    {
        "mmsi": 224166440,
        "name": "HAROMAR SEGUNDO",
        "lat": 36.53908666666667,
        "lon": -4.61701,
        "tooltip_title": "\ud83d\udea2 HAROMAR SEGUNDO",
        "tooltip_content": "MMSI: 224166440"
    },
    {
        "mmsi": 240657000,
        "name": "AEGEAN NOBILITY     ",
        "lat": 36.1577,
        "lon": -4.4078,
        "tooltip_title": "\ud83d\udea2 AEGEAN NOBILITY     ",
        "tooltip_content": "MMSI: 240657000"
    },
    {
        "mmsi": 255805764,
        "name": "OSAKA               ",
        "lat": 35.71929166666666,
        "lon": -4.622051666666667,
        "tooltip_title": "\ud83d\udea2 OSAKA               ",
        "tooltip_content": "MMSI: 255805764"
    },
    {
        "mmsi": 636023100,
        "name": "MSC JIANI           ",
        "lat": 36.64597333333334,
        "lon": -4.36951,
        "tooltip_title": "\ud83d\udea2 MSC JIANI           ",
        "tooltip_content": "MMSI: 636023100"
    },
    {
        "mmsi": 249607000,
        "name": "NATHEA-M            ",
        "lat": 36.04294,
        "lon": -5.2063749999999995,
        "tooltip_title": "\ud83d\udea2 NATHEA-M            ",
        "tooltip_content": "MMSI: 249607000"
    },
    {
        "mmsi": 538005173,
        "name": "STI DAMA            ",
        "lat": 36.135705,
        "lon": -4.169361666666666,
        "tooltip_title": "\ud83d\udea2 STI DAMA            ",
        "tooltip_content": "MMSI: 538005173"
    },
    {
        "mmsi": 224081450,
        "name": "GABRIEL Y CARMEN",
        "lat": 36.613730000000004,
        "lon": -4.3875166666666665,
        "tooltip_title": "\ud83d\udea2 GABRIEL Y CARMEN",
        "tooltip_content": "MMSI: 224081450"
    },
    {
        "mmsi": 563276400,
        "name": "KWK REVELATION      ",
        "lat": 36.20319333333334,
        "lon": -5.060081666666666,
        "tooltip_title": "\ud83d\udea2 KWK REVELATION      ",
        "tooltip_content": "MMSI: 563276400"
    },
    {
        "mmsi": 538006829,
        "name": "DS SOFIE BULKER     ",
        "lat": 35.995595,
        "lon": -5.432095,
        "tooltip_title": "\ud83d\udea2 DS SOFIE BULKER     ",
        "tooltip_content": "MMSI: 538006829"
    },
    {
        "mmsi": 255805600,
        "name": "BARBARA P           ",
        "lat": 36.14850666666667,
        "lon": -5.438053333333333,
        "tooltip_title": "\ud83d\udea2 BARBARA P           ",
        "tooltip_content": "MMSI: 255805600"
    },
    {
        "mmsi": 311001716,
        "name": "LEGEND OF THE SEAS",
        "lat": 36.35966,
        "lon": -4.308788333333334,
        "tooltip_title": "\ud83d\udea2 LEGEND OF THE SEAS",
        "tooltip_content": "MMSI: 311001716"
    },
    {
        "mmsi": 636022258,
        "name": "VIVIT AFRICA LNG    ",
        "lat": 36.26320666666666,
        "lon": -5.052881666666667,
        "tooltip_title": "\ud83d\udea2 VIVIT AFRICA LNG    ",
        "tooltip_content": "MMSI: 636022258"
    },
    {
        "mmsi": 255805917,
        "name": "OCEAN CARRIER       ",
        "lat": 36.10795333333333,
        "lon": -4.195306666666666,
        "tooltip_title": "\ud83d\udea2 OCEAN CARRIER       ",
        "tooltip_content": "MMSI: 255805917"
    },
    {
        "mmsi": 224050860,
        "name": "",
        "lat": 36.67904333333333,
        "lon": -4.436933333333333,
        "tooltip_title": "\ud83d\udea2 ",
        "tooltip_content": "MMSI: 224050860"
    },
    {
        "mmsi": 224094750,
        "name": "PAPELERO            ",
        "lat": 36.80290333333333,
        "lon": -6.3370766666666665,
        "tooltip_title": "\ud83d\udea2 PAPELERO            ",
        "tooltip_content": "MMSI: 224094750"
    },
    {
        "mmsi": 241963000,
        "name": "SEA CONDOR          ",
        "lat": 36.152280000000005,
        "lon": -4.137038333333333,
        "tooltip_title": "\ud83d\udea2 SEA CONDOR          ",
        "tooltip_content": "MMSI: 241963000"
    },
    {
        "mmsi": 224145000,
        "name": "VOLCAN DE TIMANFAYA ",
        "lat": 36.05920666666667,
        "lon": -5.121871666666666,
        "tooltip_title": "\ud83d\udea2 VOLCAN DE TIMANFAYA ",
        "tooltip_content": "MMSI: 224145000"
    },
    {
        "mmsi": 636025280,
        "name": "RIO RITA            ",
        "lat": 36.171553333333335,
        "lon": -4.824571666666667,
        "tooltip_title": "\ud83d\udea2 RIO RITA            ",
        "tooltip_content": "MMSI: 636025280"
    },
    {
        "mmsi": 224853000,
        "name": "TRHEINTAYCINCO      ",
        "lat": 36.71058,
        "lon": -4.422173333333333,
        "tooltip_title": "\ud83d\udea2 TRHEINTAYCINCO      ",
        "tooltip_content": "MMSI: 224853000"
    },
    {
        "mmsi": 636019797,
        "name": "RANGAKU             ",
        "lat": 36.057473333333334,
        "lon": -4.86269,
        "tooltip_title": "\ud83d\udea2 RANGAKU             ",
        "tooltip_content": "MMSI: 636019797"
    },
    {
        "mmsi": 538005776,
        "name": "HAFNIA ARONALDO     ",
        "lat": 36.02389,
        "lon": -5.068706666666667,
        "tooltip_title": "\ud83d\udea2 HAFNIA ARONALDO     ",
        "tooltip_content": "MMSI: 538005776"
    },
    {
        "mmsi": 224975000,
        "name": "TRHEINTAYCUATRO     ",
        "lat": 36.71067666666667,
        "lon": -4.421766666666667,
        "tooltip_title": "\ud83d\udea2 TRHEINTAYCUATRO     ",
        "tooltip_content": "MMSI: 224975000"
    },
    {
        "mmsi": 577566000,
        "name": "ASLIHAN             ",
        "lat": 36.27183333333333,
        "lon": -5.024476666666667,
        "tooltip_title": "\ud83d\udea2 ASLIHAN             ",
        "tooltip_content": "MMSI: 577566000"
    },
    {
        "mmsi": 538005401,
        "name": "STI HACKNEY         ",
        "lat": 36.13280666666667,
        "lon": -4.098463333333333,
        "tooltip_title": "\ud83d\udea2 STI HACKNEY         ",
        "tooltip_content": "MMSI: 538005401"
    },
    {
        "mmsi": 636019523,
        "name": "LISA                ",
        "lat": 35.92706166666667,
        "lon": -4.94816,
        "tooltip_title": "\ud83d\udea2 LISA                ",
        "tooltip_content": "MMSI: 636019523"
    },
    {
        "mmsi": 667002369,
        "name": "DENEB               ",
        "lat": 36.076191666666666,
        "lon": -4.344453333333333,
        "tooltip_title": "\ud83d\udea2 DENEB               ",
        "tooltip_content": "MMSI: 667002369"
    },
    {
        "mmsi": 273259530,
        "name": "BELGOROD            ",
        "lat": 35.99210333333333,
        "lon": -5.273835,
        "tooltip_title": "\ud83d\udea2 BELGOROD            ",
        "tooltip_content": "MMSI: 273259530"
    },
    {
        "mmsi": 255915584,
        "name": "BALTIC GRAIN        ",
        "lat": 36.16717666666667,
        "lon": -4.31081,
        "tooltip_title": "\ud83d\udea2 BALTIC GRAIN        ",
        "tooltip_content": "MMSI: 255915584"
    },
    {
        "mmsi": 242783300,
        "name": "SVITZER TANGER      ",
        "lat": 35.873043333333335,
        "lon": -5.534065,
        "tooltip_title": "\ud83d\udea2 SVITZER TANGER      ",
        "tooltip_content": "MMSI: 242783300"
    },
    {
        "mmsi": 563102000,
        "name": "MAERSK BALI         ",
        "lat": 35.92234166666666,
        "lon": -6.601231666666666,
        "tooltip_title": "\ud83d\udea2 MAERSK BALI         ",
        "tooltip_content": "MMSI: 563102000"
    }
]