[
    {
        "mmsi": 224975000,
        "name": "TRHEINTAYCUATRO     ",
        "lat": 36.71066666666666,
        "lon": -4.421756666666667,
        "tooltip_title": "\ud83d\udea2 TRHEINTAYCUATRO     ",
        "tooltip_content": "MMSI: 224975000"
    },
    {
        "mmsi": 225992707,
        "name": "FLY  BLUE  QUATTRO",
        "lat": 36.718025,
        "lon": -4.414056666666666,
        "tooltip_title": "\ud83d\udea2 FLY  BLUE  QUATTRO",
        "tooltip_content": "MMSI: 225992707"
    },
    {
        "mmsi": 225987877,
        "name": "SERGI I",
        "lat": 36.70236833333333,
        "lon": -4.397943333333333,
        "tooltip_title": "\ud83d\udea2 SERGI I",
        "tooltip_content": "MMSI: 225987877"
    },
    {
        "mmsi": 219836000,
        "name": "MADRID MAERSK",
        "lat": 36.31118333333333,
        "lon": -4.690916666666666,
        "tooltip_title": "\ud83d\udea2 MADRID MAERSK",
        "tooltip_content": "MMSI: 219836000"
    },
    {
        "mmsi": 304157000,
        "name": "HELENE",
        "lat": 36.480515,
        "lon": -4.375708333333334,
        "tooltip_title": "\ud83d\udea2 HELENE",
        "tooltip_content": "MMSI: 304157000"
    }
]