[
    {
        "mmsi": 636092696,
        "name": "DACHAN BAY EXPRESS  ",
        "lat": 35.74126166666667,
        "lon": -4.751320000000001,
        "tooltip_title": "\ud83d\udea2 DACHAN BAY EXPRESS  ",
        "tooltip_content": "MMSI: 636092696"
    },
    {
        "mmsi": 636022926,
        "name": "VICTORIA T          ",
        "lat": 36.197435000000006,
        "lon": -4.366373333333333,
        "tooltip_title": "\ud83d\udea2 VICTORIA T          ",
        "tooltip_content": "MMSI: 636022926"
    },
    {
        "mmsi": 219351000,
        "name": "TORM TITAN          ",
        "lat": 36.00862666666667,
        "lon": -4.499555,
        "tooltip_title": "\ud83d\udea2 TORM TITAN          ",
        "tooltip_content": "MMSI: 219351000"
    },
    {
        "mmsi": 249703000,
        "name": "HTM GRENADIER       ",
        "lat": 36.30638,
        "lon": -4.620018333333333,
        "tooltip_title": "\ud83d\udea2 HTM GRENADIER       ",
        "tooltip_content": "MMSI: 249703000"
    },
    {
        "mmsi": 255806316,
        "name": "TITLIS              ",
        "lat": 36.07113833333334,
        "lon": -4.653395000000001,
        "tooltip_title": "\ud83d\udea2 TITLIS              ",
        "tooltip_content": "MMSI: 255806316"
    },
    {
        "mmsi": 636025274,
        "name": "CONTSHIP PEP II     ",
        "lat": 36.120286666666665,
        "lon": -4.44999,
        "tooltip_title": "\ud83d\udea2 CONTSHIP PEP II     ",
        "tooltip_content": "MMSI: 636025274"
    },
    {
        "mmsi": 235112945,
        "name": "PAT BON",
        "lat": 36.46819,
        "lon": -4.709385,
        "tooltip_title": "\ud83d\udea2 PAT BON",
        "tooltip_content": "MMSI: 235112945"
    },
    {
        "mmsi": 255944000,
        "name": "GINA OLDENDORFF     ",
        "lat": 36.10459166666667,
        "lon": -4.6233683333333335,
        "tooltip_title": "\ud83d\udea2 GINA OLDENDORFF     ",
        "tooltip_content": "MMSI: 255944000"
    },
    {
        "mmsi": 210254000,
        "name": "TOSCA               ",
        "lat": 35.92079833333333,
        "lon": -4.813198333333333,
        "tooltip_title": "\ud83d\udea2 TOSCA               ",
        "tooltip_content": "MMSI: 210254000"
    },
    {
        "mmsi": 205136000,
        "name": "CL NOGARO",
        "lat": 36.755161666666666,
        "lon": -6.46557,
        "tooltip_title": "\ud83d\udea2 CL NOGARO",
        "tooltip_content": "MMSI: 205136000"
    },
    {
        "mmsi": 227920810,
        "name": "",
        "lat": 36.49098333333333,
        "lon": -4.599748333333333,
        "tooltip_title": "\ud83d\udea2 ",
        "tooltip_content": "MMSI: 227920810"
    },
    {
        "mmsi": 357795000,
        "name": "TRITON LEADER       ",
        "lat": 36.08573333333333,
        "lon": -4.938,
        "tooltip_title": "\ud83d\udea2 TRITON LEADER       ",
        "tooltip_content": "MMSI: 357795000"
    },
    {
        "mmsi": 636090856,
        "name": "LUTETIA",
        "lat": 36.224756666666664,
        "lon": -4.620806666666667,
        "tooltip_title": "\ud83d\udea2 LUTETIA",
        "tooltip_content": "MMSI: 636090856"
    },
    {
        "mmsi": 538009957,
        "name": "MARLIN LOME         ",
        "lat": 35.90251166666667,
        "lon": -4.964416666666667,
        "tooltip_title": "\ud83d\udea2 MARLIN LOME         ",
        "tooltip_content": "MMSI: 538009957"
    },
    {
        "mmsi": 224975000,
        "name": "TRHEINTAYCUATRO     ",
        "lat": 36.71067666666667,
        "lon": -4.421763333333333,
        "tooltip_title": "\ud83d\udea2 TRHEINTAYCUATRO     ",
        "tooltip_content": "MMSI: 224975000"
    },
    {
        "mmsi": 352005236,
        "name": "SELVANA             ",
        "lat": 36.19739666666667,
        "lon": -4.558213333333333,
        "tooltip_title": "\ud83d\udea2 SELVANA             ",
        "tooltip_content": "MMSI: 352005236"
    },
    {
        "mmsi": 255805866,
        "name": "MSC ELMA            ",
        "lat": 36.133183333333335,
        "lon": -4.923846666666666,
        "tooltip_title": "\ud83d\udea2 MSC ELMA            ",
        "tooltip_content": "MMSI: 255805866"
    },
    {
        "mmsi": 341640002,
        "name": "FEDERICO            ",
        "lat": 35.63511166666667,
        "lon": -4.832411666666667,
        "tooltip_title": "\ud83d\udea2 FEDERICO            ",
        "tooltip_content": "MMSI: 341640002"
    },
    {
        "mmsi": 225996458,
        "name": "",
        "lat": 36.559531666666665,
        "lon": -4.535816666666666,
        "tooltip_title": "\ud83d\udea2 ",
        "tooltip_content": "MMSI: 225996458"
    },
    {
        "mmsi": 215459000,
        "name": "KAVOKAMILI          ",
        "lat": 36.155303333333336,
        "lon": -4.980238333333333,
        "tooltip_title": "\ud83d\udea2 KAVOKAMILI          ",
        "tooltip_content": "MMSI: 215459000"
    },
    {
        "mmsi": 212302000,
        "name": "HERCULES J",
        "lat": 36.13167833333333,
        "lon": -4.09213,
        "tooltip_title": "\ud83d\udea2 HERCULES J",
        "tooltip_content": "MMSI: 212302000"
    },
    {
        "mmsi": 235069089,
        "name": "WO AI NI",
        "lat": 36.54107833333333,
        "lon": -4.617265000000001,
        "tooltip_title": "\ud83d\udea2 WO AI NI",
        "tooltip_content": "MMSI: 235069089"
    },
    {
        "mmsi": 224166440,
        "name": "HAROMAR SEGUNDO",
        "lat": 36.53971,
        "lon": -4.618415,
        "tooltip_title": "\ud83d\udea2 HAROMAR SEGUNDO",
        "tooltip_content": "MMSI: 224166440"
    },
    {
        "mmsi": 225994677,
        "name": "TUNITA FOUR",
        "lat": 36.574085,
        "lon": -4.5362599999999995,
        "tooltip_title": "\ud83d\udea2 TUNITA FOUR",
        "tooltip_content": "MMSI: 225994677"
    },
    {
        "mmsi": 477979200,
        "name": "PHOSPHOR            ",
        "lat": 35.80670333333333,
        "lon": -4.923588333333333,
        "tooltip_title": "\ud83d\udea2 PHOSPHOR            ",
        "tooltip_content": "MMSI: 477979200"
    },
    {
        "mmsi": 209575000,
        "name": "CONTSHIP PAX",
        "lat": 36.032383333333335,
        "lon": -5.295401666666667,
        "tooltip_title": "\ud83d\udea2 CONTSHIP PAX",
        "tooltip_content": "MMSI: 209575000"
    },
    {
        "mmsi": 215000668,
        "name": "NYUMBA R",
        "lat": 36.70823333333333,
        "lon": -4.415146666666667,
        "tooltip_title": "\ud83d\udea2 NYUMBA R",
        "tooltip_content": "MMSI: 215000668"
    },
    {
        "mmsi": 249804000,
        "name": "SUMMER LADY         ",
        "lat": 36.07380166666667,
        "lon": -5.28803,
        "tooltip_title": "\ud83d\udea2 SUMMER LADY         ",
        "tooltip_content": "MMSI: 249804000"
    },
    {
        "mmsi": 257729000,
        "name": "SIGAIA THERESA      ",
        "lat": 36.20283666666667,
        "lon": -4.838821666666666,
        "tooltip_title": "\ud83d\udea2 SIGAIA THERESA      ",
        "tooltip_content": "MMSI: 257729000"
    },
    {
        "mmsi": 447302000,
        "name": "AL KUWAIT           ",
        "lat": 35.959468333333334,
        "lon": -4.901563333333333,
        "tooltip_title": "\ud83d\udea2 AL KUWAIT           ",
        "tooltip_content": "MMSI: 447302000"
    }
]