[
    {
        "mmsi": 538010807,
        "name": "AQUAVITA WEALTH     ",
        "lat": 36.071313333333336,
        "lon": -5.0774349999999995,
        "tooltip_title": "\ud83d\udea2 AQUAVITA WEALTH     ",
        "tooltip_content": "MMSI: 538010807"
    },
    {
        "mmsi": 636025443,
        "name": "CAPRI               ",
        "lat": 35.773133333333334,
        "lon": -4.96612,
        "tooltip_title": "\ud83d\udea2 CAPRI               ",
        "tooltip_content": "MMSI: 636025443"
    },
    {
        "mmsi": 636019093,
        "name": "BERGE TRIGLAV       ",
        "lat": 36.27220333333333,
        "lon": -4.875236666666667,
        "tooltip_title": "\ud83d\udea2 BERGE TRIGLAV       ",
        "tooltip_content": "MMSI: 636019093"
    },
    {
        "mmsi": 538007273,
        "name": "IRON LADY           ",
        "lat": 36.31064166666667,
        "lon": -4.812425,
        "tooltip_title": "\ud83d\udea2 IRON LADY           ",
        "tooltip_content": "MMSI: 538007273"
    },
    {
        "mmsi": 352004122,
        "name": "AAPUS 11            ",
        "lat": 36.1811,
        "lon": -4.99275,
        "tooltip_title": "\ud83d\udea2 AAPUS 11            ",
        "tooltip_content": "MMSI: 352004122"
    },
    {
        "mmsi": 538009150,
        "name": "PRINCESS GRACE      ",
        "lat": 36.151068333333335,
        "lon": -5.034203333333334,
        "tooltip_title": "\ud83d\udea2 PRINCESS GRACE      ",
        "tooltip_content": "MMSI: 538009150"
    },
    {
        "mmsi": 210329000,
        "name": "RUSADIR",
        "lat": 36.43108666666667,
        "lon": -4.099241666666667,
        "tooltip_title": "\ud83d\udea2 RUSADIR",
        "tooltip_content": "MMSI: 210329000"
    },
    {
        "mmsi": 636025571,
        "name": "JAXSON              ",
        "lat": 35.82544,
        "lon": -4.629818333333334,
        "tooltip_title": "\ud83d\udea2 JAXSON              ",
        "tooltip_content": "MMSI: 636025571"
    },
    {
        "mmsi": 229988000,
        "name": "CMA CGM TAGE",
        "lat": 36.19813666666666,
        "lon": -4.0248116666666665,
        "tooltip_title": "\ud83d\udea2 CMA CGM TAGE",
        "tooltip_content": "MMSI: 229988000"
    },
    {
        "mmsi": 225999847,
        "name": "LEAL",
        "lat": 36.71469666666667,
        "lon": -4.345103333333333,
        "tooltip_title": "\ud83d\udea2 LEAL",
        "tooltip_content": "MMSI: 225999847"
    },
    {
        "mmsi": 563279900,
        "name": "SEASPAN EMISSARY    ",
        "lat": 35.979670000000006,
        "lon": -5.369221666666666,
        "tooltip_title": "\ud83d\udea2 SEASPAN EMISSARY    ",
        "tooltip_content": "MMSI: 563279900"
    },
    {
        "mmsi": 255805849,
        "name": "ULANGA",
        "lat": 36.247933333333336,
        "lon": -4.91045,
        "tooltip_title": "\ud83d\udea2 ULANGA",
        "tooltip_content": "MMSI: 255805849"
    },
    {
        "mmsi": 224975000,
        "name": "TRHEINTAYCUATRO     ",
        "lat": 36.710675,
        "lon": -4.421761666666667,
        "tooltip_title": "\ud83d\udea2 TRHEINTAYCUATRO     ",
        "tooltip_content": "MMSI: 224975000"
    },
    {
        "mmsi": 304690000,
        "name": "TANJA               ",
        "lat": 36.0486,
        "lon": -4.956105,
        "tooltip_title": "\ud83d\udea2 TANJA               ",
        "tooltip_content": "MMSI: 304690000"
    },
    {
        "mmsi": 538009882,
        "name": "CUMBIA 1            ",
        "lat": 36.331855000000004,
        "lon": -4.60092,
        "tooltip_title": "\ud83d\udea2 CUMBIA 1            ",
        "tooltip_content": "MMSI: 538009882"
    },
    {
        "mmsi": 538011392,
        "name": "FERUSA R            ",
        "lat": 36.151086666666664,
        "lon": -4.944038333333333,
        "tooltip_title": "\ud83d\udea2 FERUSA R            ",
        "tooltip_content": "MMSI: 538011392"
    },
    {
        "mmsi": 538004030,
        "name": "SEAWAYS FRIO        ",
        "lat": 36.218136666666666,
        "lon": -4.854221666666667,
        "tooltip_title": "\ud83d\udea2 SEAWAYS FRIO        ",
        "tooltip_content": "MMSI: 538004030"
    },
    {
        "mmsi": 242123456,
        "name": "SEMAPHORE           ",
        "lat": 35.75269333333333,
        "lon": -5.340215,
        "tooltip_title": "\ud83d\udea2 SEMAPHORE           ",
        "tooltip_content": "MMSI: 242123456"
    },
    {
        "mmsi": 229259000,
        "name": "DENSA DERYA         ",
        "lat": 36.77137666666667,
        "lon": -6.461856666666667,
        "tooltip_title": "\ud83d\udea2 DENSA DERYA         ",
        "tooltip_content": "MMSI: 229259000"
    },
    {
        "mmsi": 412760000,
        "name": "BAO RUI LING        ",
        "lat": 36.11757333333333,
        "lon": -5.010583333333333,
        "tooltip_title": "\ud83d\udea2 BAO RUI LING        ",
        "tooltip_content": "MMSI: 412760000"
    },
    {
        "mmsi": 636022180,
        "name": "MINERVA ANNA        ",
        "lat": 36.12397,
        "lon": -4.869441666666666,
        "tooltip_title": "\ud83d\udea2 MINERVA ANNA        ",
        "tooltip_content": "MMSI: 636022180"
    },
    {
        "mmsi": 636025346,
        "name": "MSC MARIE LESLIE    ",
        "lat": 36.203176666666664,
        "lon": -4.831194999999999,
        "tooltip_title": "\ud83d\udea2 MSC MARIE LESLIE    ",
        "tooltip_content": "MMSI: 636025346"
    },
    {
        "mmsi": 244848000,
        "name": "DONAUGRACHT         ",
        "lat": 36.215241666666664,
        "lon": -4.23585,
        "tooltip_title": "\ud83d\udea2 DONAUGRACHT         ",
        "tooltip_content": "MMSI: 244848000"
    },
    {
        "mmsi": 225993919,
        "name": "DOUBBLE TROUBBLE    ",
        "lat": 36.71401,
        "lon": -4.344751666666666,
        "tooltip_title": "\ud83d\udea2 DOUBBLE TROUBBLE    ",
        "tooltip_content": "MMSI: 225993919"
    },
    {
        "mmsi": 636018011,
        "name": "KINISIS             ",
        "lat": 36.141241666666666,
        "lon": -5.007765,
        "tooltip_title": "\ud83d\udea2 KINISIS             ",
        "tooltip_content": "MMSI: 636018011"
    }
]