[
    {
        "mmsi": 224057990,
        "name": "NUEVO TALITO SEGUNDO",
        "lat": 36.77352,
        "lon": -6.414811666666666,
        "tooltip_title": "\ud83d\udea2 NUEVO TALITO SEGUNDO",
        "tooltip_content": "MMSI: 224057990"
    },
    {
        "mmsi": 224009880,
        "name": "PLAYA MORCH SG",
        "lat": 36.4776,
        "lon": -4.640716666666666,
        "tooltip_title": "\ud83d\udea2 PLAYA MORCH SG",
        "tooltip_content": "MMSI: 224009880"
    },
    {
        "mmsi": 240893000,
        "name": "MARAN PYTHIA        ",
        "lat": 36.09531666666667,
        "lon": -5.012433333333333,
        "tooltip_title": "\ud83d\udea2 MARAN PYTHIA        ",
        "tooltip_content": "MMSI: 240893000"
    },
    {
        "mmsi": 431536000,
        "name": "OCEANUS HIGHWAY     ",
        "lat": 36.19336666666666,
        "lon": -5.024481666666667,
        "tooltip_title": "\ud83d\udea2 OCEANUS HIGHWAY     ",
        "tooltip_content": "MMSI: 431536000"
    },
    {
        "mmsi": 241734000,
        "name": "MINERVA ALEXANDRA   ",
        "lat": 35.699963333333336,
        "lon": -4.877743333333333,
        "tooltip_title": "\ud83d\udea2 MINERVA ALEXANDRA   ",
        "tooltip_content": "MMSI: 241734000"
    },
    {
        "mmsi": 224853000,
        "name": "TRHEINTAYCINCO      ",
        "lat": 36.710566666666665,
        "lon": -4.4222,
        "tooltip_title": "\ud83d\udea2 TRHEINTAYCINCO      ",
        "tooltip_content": "MMSI: 224853000"
    },
    {
        "mmsi": 538012644,
        "name": "HTM HIGHLANDER      ",
        "lat": 36.098866666666666,
        "lon": -5.098565,
        "tooltip_title": "\ud83d\udea2 HTM HIGHLANDER      ",
        "tooltip_content": "MMSI: 538012644"
    },
    {
        "mmsi": 248171000,
        "name": "EPIC BORINQUEN      ",
        "lat": 36.26247166666667,
        "lon": -4.212556666666667,
        "tooltip_title": "\ud83d\udea2 EPIC BORINQUEN      ",
        "tooltip_content": "MMSI: 248171000"
    },
    {
        "mmsi": 255834000,
        "name": "HERBANIA            ",
        "lat": 36.15084,
        "lon": -4.0238949999999996,
        "tooltip_title": "\ud83d\udea2 HERBANIA            ",
        "tooltip_content": "MMSI: 255834000"
    },
    {
        "mmsi": 636021664,
        "name": "ZIM ASIA            ",
        "lat": 36.14590166666667,
        "lon": -4.358255,
        "tooltip_title": "\ud83d\udea2 ZIM ASIA            ",
        "tooltip_content": "MMSI: 636021664"
    },
    {
        "mmsi": 224133860,
        "name": "HERMANOS HDEZ.GARCIA",
        "lat": 36.237161666666665,
        "lon": -5.086073333333333,
        "tooltip_title": "\ud83d\udea2 HERMANOS HDEZ.GARCIA",
        "tooltip_content": "MMSI: 224133860"
    },
    {
        "mmsi": 636020727,
        "name": "BLUE ONE            ",
        "lat": 36.19043833333333,
        "lon": -4.468226666666666,
        "tooltip_title": "\ud83d\udea2 BLUE ONE            ",
        "tooltip_content": "MMSI: 636020727"
    },
    {
        "mmsi": 538003141,
        "name": "EQUATOR             ",
        "lat": 36.25072,
        "lon": -4.832269999999999,
        "tooltip_title": "\ud83d\udea2 EQUATOR             ",
        "tooltip_content": "MMSI: 538003141"
    },
    {
        "mmsi": 305433000,
        "name": "CATALINA            ",
        "lat": 36.19239666666667,
        "lon": -4.948015,
        "tooltip_title": "\ud83d\udea2 CATALINA            ",
        "tooltip_content": "MMSI: 305433000"
    },
    {
        "mmsi": 538011019,
        "name": "ACHELOOS            ",
        "lat": 35.91296166666667,
        "lon": -4.963835,
        "tooltip_title": "\ud83d\udea2 ACHELOOS            ",
        "tooltip_content": "MMSI: 538011019"
    },
    {
        "mmsi": 224241390,
        "name": "NUEVO HARO RODRIGUEZ",
        "lat": 36.485933333333335,
        "lon": -4.61864,
        "tooltip_title": "\ud83d\udea2 NUEVO HARO RODRIGUEZ",
        "tooltip_content": "MMSI: 224241390"
    },
    {
        "mmsi": 255916096,
        "name": "IVER BEST           ",
        "lat": 36.132978333333334,
        "lon": -4.175391666666667,
        "tooltip_title": "\ud83d\udea2 IVER BEST           ",
        "tooltip_content": "MMSI: 255916096"
    }
]