[
    {
        "mmsi": 636016702,
        "name": "MSC OAK F",
        "lat": 36.706925,
        "lon": -4.419088333333334,
        "tooltip_title": "\ud83d\udea2 MSC OAK F",
        "tooltip_content": "MMSI: 636016702"
    },
    {
        "mmsi": 256536000,
        "name": "LEVANTE LNG         ",
        "lat": 36.120628333333336,
        "lon": -4.253805,
        "tooltip_title": "\ud83d\udea2 LEVANTE LNG         ",
        "tooltip_content": "MMSI: 256536000"
    },
    {
        "mmsi": 235073273,
        "name": "",
        "lat": 36.54214833333333,
        "lon": -4.61782,
        "tooltip_title": "\ud83d\udea2 ",
        "tooltip_content": "MMSI: 235073273"
    },
    {
        "mmsi": 255805849,
        "name": "ULANGA",
        "lat": 36.270316666666666,
        "lon": -4.7702,
        "tooltip_title": "\ud83d\udea2 ULANGA",
        "tooltip_content": "MMSI: 255805849"
    },
    {
        "mmsi": 566722000,
        "name": "KINGSTON            ",
        "lat": 36.1048,
        "lon": -4.419645,
        "tooltip_title": "\ud83d\udea2 KINGSTON            ",
        "tooltip_content": "MMSI: 566722000"
    },
    {
        "mmsi": 538010356,
        "name": "ANGELA GLORY        ",
        "lat": 36.01588166666667,
        "lon": -4.994524999999999,
        "tooltip_title": "\ud83d\udea2 ANGELA GLORY        ",
        "tooltip_content": "MMSI: 538010356"
    },
    {
        "mmsi": 538008685,
        "name": "POOLE               ",
        "lat": 35.82606333333333,
        "lon": -5.099241666666667,
        "tooltip_title": "\ud83d\udea2 POOLE               ",
        "tooltip_content": "MMSI: 538008685"
    },
    {
        "mmsi": 249906000,
        "name": "FU ZHOU WAN         ",
        "lat": 36.08548666666666,
        "lon": -4.47168,
        "tooltip_title": "\ud83d\udea2 FU ZHOU WAN         ",
        "tooltip_content": "MMSI: 249906000"
    },
    {
        "mmsi": 210312000,
        "name": "WEC MAJORELLE",
        "lat": 36.184868333333334,
        "lon": -4.216428333333334,
        "tooltip_title": "\ud83d\udea2 WEC MAJORELLE",
        "tooltip_content": "MMSI: 210312000"
    },
    {
        "mmsi": 367564330,
        "name": "ERAORA",
        "lat": 36.718176666666665,
        "lon": -4.41412,
        "tooltip_title": "\ud83d\udea2 ERAORA",
        "tooltip_content": "MMSI: 367564330"
    },
    {
        "mmsi": 255806060,
        "name": "JOHN AUGUSTUS ESSBER",
        "lat": 35.93407666666667,
        "lon": -5.26556,
        "tooltip_title": "\ud83d\udea2 JOHN AUGUSTUS ESSBER",
        "tooltip_content": "MMSI: 255806060"
    },
    {
        "mmsi": 224853000,
        "name": "TRHEINTAYCINCO      ",
        "lat": 36.71056,
        "lon": -4.422185,
        "tooltip_title": "\ud83d\udea2 TRHEINTAYCINCO      ",
        "tooltip_content": "MMSI: 224853000"
    },
    {
        "mmsi": 352003982,
        "name": "MAGIC CHEMIST       ",
        "lat": 36.215803333333334,
        "lon": -4.9449266666666665,
        "tooltip_title": "\ud83d\udea2 MAGIC CHEMIST       ",
        "tooltip_content": "MMSI: 352003982"
    },
    {
        "mmsi": 224094750,
        "name": "PAPELERO            ",
        "lat": 36.80390666666666,
        "lon": -6.337206666666666,
        "tooltip_title": "\ud83d\udea2 PAPELERO            ",
        "tooltip_content": "MMSI: 224094750"
    },
    {
        "mmsi": 253000181,
        "name": "THEANOULA           ",
        "lat": 36.23943166666666,
        "lon": -5.071096666666667,
        "tooltip_title": "\ud83d\udea2 THEANOULA           ",
        "tooltip_content": "MMSI: 253000181"
    },
    {
        "mmsi": 273414440,
        "name": "ADLER",
        "lat": 35.971875,
        "lon": -5.001441666666667,
        "tooltip_title": "\ud83d\udea2 ADLER",
        "tooltip_content": "MMSI: 273414440"
    },
    {
        "mmsi": 636022736,
        "name": "TATIANA             ",
        "lat": 36.056841666666664,
        "lon": -5.057334999999999,
        "tooltip_title": "\ud83d\udea2 TATIANA             ",
        "tooltip_content": "MMSI: 636022736"
    },
    {
        "mmsi": 244129000,
        "name": "POOLGRACHT          ",
        "lat": 36.024175,
        "lon": -4.922371666666667,
        "tooltip_title": "\ud83d\udea2 POOLGRACHT          ",
        "tooltip_content": "MMSI: 244129000"
    },
    {
        "mmsi": 236509000,
        "name": "MITTELPLATE         ",
        "lat": 36.78003666666667,
        "lon": -6.393255,
        "tooltip_title": "\ud83d\udea2 MITTELPLATE         ",
        "tooltip_content": "MMSI: 236509000"
    },
    {
        "mmsi": 304905000,
        "name": "CELTIC EXPLORER     ",
        "lat": 36.074025,
        "lon": -4.216268333333334,
        "tooltip_title": "\ud83d\udea2 CELTIC EXPLORER     ",
        "tooltip_content": "MMSI: 304905000"
    },
    {
        "mmsi": 538009200,
        "name": "PACIFIC SAPPHIRE    ",
        "lat": 36.27024333333333,
        "lon": -4.90036,
        "tooltip_title": "\ud83d\udea2 PACIFIC SAPPHIRE    ",
        "tooltip_content": "MMSI: 538009200"
    },
    {
        "mmsi": 212561000,
        "name": "CEUTA JET           ",
        "lat": 35.894575,
        "lon": -5.3137,
        "tooltip_title": "\ud83d\udea2 CEUTA JET           ",
        "tooltip_content": "MMSI: 212561000"
    },
    {
        "mmsi": 255806143,
        "name": "AVILA",
        "lat": 36.25642333333334,
        "lon": -4.741068333333333,
        "tooltip_title": "\ud83d\udea2 AVILA",
        "tooltip_content": "MMSI: 255806143"
    },
    {
        "mmsi": 636025766,
        "name": "ESPADA X            ",
        "lat": 36.26728833333333,
        "lon": -4.967903333333334,
        "tooltip_title": "\ud83d\udea2 ESPADA X            ",
        "tooltip_content": "MMSI: 636025766"
    },
    {
        "mmsi": 244850075,
        "name": "ARKLOW BREEZE",
        "lat": 36.45536166666667,
        "lon": -4.178328333333334,
        "tooltip_title": "\ud83d\udea2 ARKLOW BREEZE",
        "tooltip_content": "MMSI: 244850075"
    },
    {
        "mmsi": 636014169,
        "name": "CMA CGM TOPAZ       ",
        "lat": 35.99919666666666,
        "lon": -5.025363333333333,
        "tooltip_title": "\ud83d\udea2 CMA CGM TOPAZ       ",
        "tooltip_content": "MMSI: 636014169"
    },
    {
        "mmsi": 209887000,
        "name": "LEDRA DYNAMIC",
        "lat": 35.597361666666664,
        "lon": -4.803465,
        "tooltip_title": "\ud83d\udea2 LEDRA DYNAMIC",
        "tooltip_content": "MMSI: 209887000"
    }
]